sphinxcontrib/umlet/__init__.py
sphinxcontrib/umlet/umlet.css
sphinxcontrib_umlet-1.0.2.dist-info/LICENSE
sphinxcontrib_umlet-1.0.2.dist-info/METADATA
sphinxcontrib_umlet-1.0.2.dist-info/WHEEL
sphinxcontrib_umlet-1.0.2.dist-info/top_level.txt
sphinxcontrib_umlet-1.0.2.dist-info/RECORD
