Metadata-Version: 2.1
Name: sphinxcontrib-umlet
Version: 1.0.2
Summary: Sphinx Extension to embed UMLet diagrams
Home-page: https://github.com/basejumpa/sphinxcontrib-umlet
Author: Alexander Mann-Wahrenberg (basejumpa)
Author-email: alexander.mannwahrenberg@gmail.com
License: MIT
Classifier: Programming Language :: Python :: 3
Classifier: License :: OSI Approved :: MIT License
Classifier: Operating System :: OS Independent
Classifier: Framework :: Sphinx :: Extension
Requires-Python: >=3.7
License-File: LICENSE
Requires-Dist: sphinx (>=2)
